LaTeXDatax/__init__.py
LaTeXDatax/datax.py
tests/__init__.py
tests/test_LaTeXDatax.py
LaTeXDatax-1.3.dist-info/LICENSE
LaTeXDatax-1.3.dist-info/METADATA
LaTeXDatax-1.3.dist-info/WHEEL
LaTeXDatax-1.3.dist-info/top_level.txt
LaTeXDatax-1.3.dist-info/RECORD
