Metadata-Version: 2.1
Name: LaTeXDatax
Version: 1.3
Summary: Export individual data from a Python script to a LaTeX document
Home-page: https://github.com/Datax-package/LaTeXDatax.py
Author: David Gustavsson
Author-email: david.e.gustavsson@gmail.com
License: UNKNOWN
Platform: UNKNOWN
Classifier: Programming Language :: Python :: 3
Classifier: License :: OSI Approved :: MIT License
Classifier: Operating System :: OS Independent
Requires-Python: >=3.6
License-File: LICENSE
